cytocoarsening/__init__.py
cytocoarsening/cytocoarsening.py
cytocoarsening/evaluate.py
cytocoarsening-0.0.8.dist-info/LICENSE
cytocoarsening-0.0.8.dist-info/METADATA
cytocoarsening-0.0.8.dist-info/WHEEL
cytocoarsening-0.0.8.dist-info/top_level.txt
cytocoarsening-0.0.8.dist-info/RECORD
