Metadata-Version: 2.1
Name: cytocoarsening
Version: 0.0.8
Summary: cytocoarsening-graph coarsening
Home-page: https://github.com/catchzeng/cytocoarsening
Author: ChiJaneChen
Author-email: cookie877128@gmail.com
Classifier: Programming Language :: Python :: 3
Classifier: License :: OSI Approved :: MIT License
Classifier: Operating System :: OS Independent
Requires-Python: >=3.7
License-File: LICENSE
Requires-Dist: scikit-learn (>=0.24.1)
Requires-Dist: numpy (>=1.20.1)
Requires-Dist: networkx (>=2.6.2)
